<annotation>
  <folder>VOC2014_instance/traffic light</folder>
  <filename>000000015272.jpg</filename>
  <source>
    <database>MS COCO 2014</database>
    <annotation>MS COCO 2014</annotation>
    <image>Flickr</image>
    <url>http://images.cocodataset.org/val2017/000000015272.jpg</url>
  </source>
  <size>
    <width>424</width>
    <height>640</height>
    <depth>3</depth>
  </size>
  <segmented>0</segmented>
  <object>
    <name>traffic light</name>
    <bndbox>
      <xmin>41.95</xmin>
      <ymin>38.91</ymin>
      <xmax>276.42</xmax>
      <ymax>136.78</ymax>
    </bndbox>
    <difficult>0</difficult>
  </object>
</annotation>
