<annotation verified="yes">
    <folder>Annotation</folder>
    <filename>adimg44.jpg</filename>
    <path>can_img-PascalVOC-export/Annotations/adimg44.jpg</path>
    <source>
        <database>Unknown</database>
    </source>
    <size>
        <width>1908</width>
        <height>1146</height>
        <depth>3</depth>
    </size>
    <segmented>0</segmented>
    <object>
    <name>can</name>
    <pose>Unspecified</pose>
    <truncated>0</truncated>
    <difficult>0</difficult>
    <bndbox>
        <xmin>0</xmin>
        <ymin>26.393855804111244</ymin>
        <xmax>171.81699346405227</xmax>
        <ymax>584.8436744256348</ymax>
    </bndbox>
</object><object>
    <name>can</name>
    <pose>Unspecified</pose>
    <truncated>0</truncated>
    <difficult>0</difficult>
    <bndbox>
        <xmin>8.313725490196077</xmin>
        <ymin>594.5437953446191</ymin>
        <xmax>175.9738562091503</xmax>
        <ymax>1112.8073987303505</ymax>
    </bndbox>
</object><object>
    <name>can</name>
    <pose>Unspecified</pose>
    <truncated>0</truncated>
    <difficult>0</difficult>
    <bndbox>
        <xmin>191.2156862745098</xmin>
        <ymin>25.008124244256347</ymin>
        <xmax>472.49673202614383</xmax>
        <ymax>576.5292850665054</ymax>
    </bndbox>
</object><object>
    <name>can</name>
    <pose>Unspecified</pose>
    <truncated>0</truncated>
    <difficult>0</difficult>
    <bndbox>
        <xmin>205.07189542483658</xmin>
        <ymin>584.8436744256348</ymin>
        <xmax>471.1111111111111</xmax>
        <ymax>1116.9645934099153</ymax>
    </bndbox>
</object><object>
    <name>can</name>
    <pose>Unspecified</pose>
    <truncated>0</truncated>
    <difficult>0</difficult>
    <bndbox>
        <xmin>484.9673202614379</xmin>
        <ymin>575.1435535066505</ymin>
        <xmax>759.3202614379086</xmax>
        <ymax>1101.7215462515114</ymax>
    </bndbox>
</object><object>
    <name>can</name>
    <pose>Unspecified</pose>
    <truncated>0</truncated>
    <difficult>0</difficult>
    <bndbox>
        <xmin>482.19607843137254</xmin>
        <ymin>23.62239268440145</ymin>
        <xmax>746.8496732026144</xmax>
        <ymax>569.600627267231</ymax>
    </bndbox>
</object><object>
    <name>can</name>
    <pose>Unspecified</pose>
    <truncated>0</truncated>
    <difficult>0</difficult>
    <bndbox>
        <xmin>763.4771241830065</xmin>
        <ymin>19.465198004836758</ymin>
        <xmax>1050.3006535947711</xmax>
        <ymax>577.9150166263604</ymax>
    </bndbox>
</object><object>
    <name>can</name>
    <pose>Unspecified</pose>
    <truncated>0</truncated>
    <difficult>0</difficult>
    <bndbox>
        <xmin>767.6339869281046</xmin>
        <ymin>589.0008691051995</ymin>
        <xmax>1041.9869281045753</xmax>
        <ymax>1122.5075196493349</ymax>
    </bndbox>
</object><object>
    <name>can</name>
    <pose>Unspecified</pose>
    <truncated>0</truncated>
    <difficult>0</difficult>
    <bndbox>
        <xmin>1055.8431372549019</xmin>
        <ymin>16.693734885126965</ymin>
        <xmax>1352.3660130718954</xmax>
        <ymax>564.0577010278114</ymax>
    </bndbox>
</object><object>
    <name>can</name>
    <pose>Unspecified</pose>
    <truncated>0</truncated>
    <difficult>0</difficult>
    <bndbox>
        <xmin>1046.1437908496732</xmin>
        <ymin>570.9863588270858</ymin>
        <xmax>1344.0522875816994</xmax>
        <ymax>1136.364835247884</ymax>
    </bndbox>
</object><object>
    <name>can</name>
    <pose>Unspecified</pose>
    <truncated>0</truncated>
    <difficult>0</difficult>
    <bndbox>
        <xmin>1352.3660130718954</xmin>
        <ymin>12.536540205562273</ymin>
        <xmax>1650.2745098039215</xmax>
        <ymax>572.3720903869407</ymax>
    </bndbox>
</object><object>
    <name>can</name>
    <pose>Unspecified</pose>
    <truncated>0</truncated>
    <difficult>0</difficult>
    <bndbox>
        <xmin>1339.8954248366013</xmin>
        <ymin>584.8436744256348</ymin>
        <xmax>1626.718954248366</xmax>
        <ymax>1128.0504458887544</ymax>
    </bndbox>
</object><object>
    <name>can</name>
    <pose>Unspecified</pose>
    <truncated>0</truncated>
    <difficult>0</difficult>
    <bndbox>
        <xmin>1641.9607843137255</xmin>
        <ymin>25.008124244256347</ymin>
        <xmax>1902.4575163398692</xmax>
        <ymax>594.5437953446191</ymax>
    </bndbox>
</object><object>
    <name>can</name>
    <pose>Unspecified</pose>
    <truncated>0</truncated>
    <difficult>0</difficult>
    <bndbox>
        <xmin>1635.0326797385621</xmin>
        <ymin>604.2439162636034</ymin>
        <xmax>1908</xmax>
        <ymax>1146</ymax>
    </bndbox>
</object>
</annotation>
