<annotation verified="yes">
    <folder>Annotation</folder>
    <filename>adimg72.jpg</filename>
    <path>can_img-PascalVOC-export/Annotations/adimg72.jpg</path>
    <source>
        <database>Unknown</database>
    </source>
    <size>
        <width>166</width>
        <height>303</height>
        <depth>3</depth>
    </size>
    <segmented>0</segmented>
    <object>
    <name>can</name>
    <pose>Unspecified</pose>
    <truncated>0</truncated>
    <difficult>0</difficult>
    <bndbox>
        <xmin>10.461638830897703</xmin>
        <ymin>30.126857142857144</ymin>
        <xmax>157.0545407098121</xmax>
        <ymax>290.1874285714286</ymax>
    </bndbox>
</object>
</annotation>
