<annotation verified="yes">
    <folder>Annotation</folder>
    <filename>can_img134.jpg</filename>
    <path>can_img-PascalVOC-export/Annotations/can_img134.jpg</path>
    <source>
        <database>Unknown</database>
    </source>
    <size>
        <width>800</width>
        <height>600</height>
        <depth>3</depth>
    </size>
    <segmented>0</segmented>
    <object>
    <name>can</name>
    <pose>Unspecified</pose>
    <truncated>0</truncated>
    <difficult>0</difficult>
    <bndbox>
        <xmin>236.64459161147903</xmin>
        <ymin>88.8970588235294</ymin>
        <xmax>572.1854304635762</xmax>
        <ymax>595.3676470588235</ymax>
    </bndbox>
</object>
</annotation>
